Workbook

Sheet Oct 2023
A1: 💸 OCT 2023 — GASTOS MENSUALES
A2: USD/ARS | B2: 960 | C2: ← update monthly
A3: ▲ INGRESOS
A4: # | B4: Source | C4: Description | D4: ARS | E4: USD
A5: 1 | C5: Lucas Food Truck 35k | D5: 35000 | E5: 36.46
A6: 2 | C6: R Zapas Tincho Vans Bordo | D6: 30000 | E6: 31.25
A7: 3 | C7: D Dani 530 | D7: 502080 | E7: 523
A8: 4 | C8: R Casaca River Negra | D8: 15000 | E8: 15.63
A9: 5 | C9: V Vapos x3 | D9: 32200 | E9: 33.54
A10: 6 | C10: F1 A Hs82 y Tom saez | D10: 127400 | E10: 132.71
A11: 7 | C11: M MODEL PEYA | D11: 200000 | E11: 208.33
A12: 8 | C12: A Iphone Gonza CF 13Pro 98% | D12: 100800 | E12: 105
A13: 9 | C13: A Ipad 9na | D13: 90000 | E13: 93.75
A14: TOTAL INGRESOS | D14: =SUM(D5:D13) | E14: =SUM(E5:E13)
A16: ▼ EGRESOS FIJOS
A17: # | B17: Description | C17: ARS | D17: USD | E17: Status
A18: 1 | B18: Rentas | D18: 6000 | E18: 6.06 | F18: Pagado
A19: 2 | B19: Exp Arenales | D19: 9000 | E19: 9.09 | F19: Pagado
A20: 3 | B20: AFIP | D20: 5500 | E20: 5.56 | F20: Pagado
A21: 4 | B21: Boca | D21: 2500 | E21: 2.53 | F21: Auto
A22: 5 | B22: Smiles | D22: 3500 | E22: 3.54 | F22: Auto
A23: 6 | B23: Gali Prestamo | D23: 15500 | E23: 15.66 | F23: Pendiente
A24: 7 | B24: BBVA Tarjeta | D24: 10000 | E24: 10.1 | F24: Pagado
A25: TOTAL FIJOS | D25: =SUM(D18:D24) | E25: =SUM(E18:E24)
A27: 📋 GASTOS DEL MES
A28: # | B28: Date | C28: Description | D28: ARS | E28: USD | F28: Category | G28: Payment
A29: 1 | B29: 01 | C29: 1er pago Cabaña | D29: 50000 | E29: 52.08
A30: 2 | B30: 02 | C30: Veggie | D30: 4000 | E30: 4.17
A31: 3 | B31: 03 | C31: 2do Pago Cabaña | D31: 118000 | E31: 122.92
A32: 4 | B32: 04 | C32: Tarta | D32: 5000 | E32: 5.21
A33: 5 | B33: 05 | C33: Compras Depto | D33: 18000 | E33: 18.75
A34: 6 | B34: 06 | C34: Pava Electrica | D34: 7000 | E34: 7.29
A35: 7 | B35: 07 | C35: Tapa de baño | D35: 11000 | E35: 11.46
A36: 8 | B36: 08 | C36: Casaca Barza | D36: 7000 | E36: 7.29
A37: 9 | B37: 09 | C37: Polleria | D37: 10000 | E37: 10.42
A38: 10 | B38: 10 | C38: Kiosco | D38: 5000 | E38: 5.21
A54: TOTAL VARIABLE | D54: =SUM(D29:D53) | E54: =SUM(E29:E53)
A56: 💰 BALANCE | D56: =D14-D25-D54 | E56: =E14-E25-E54

Sheet Nov 2023
A1: 💸 NOV 2023 — GASTOS MENSUALES
A2: USD/ARS | B2: 960 | C2: ← update monthly
A3: ▲ INGRESOS
A4: # | B4: Source | C4: Description | D4: ARS | E4: USD
A5: 1 | C5: D Dani | D5: 500000 | E5: 500
A6: 2 | C6: R Oakley | D6: 140000 | E6: 145.83
A7: 3 | C7: F Feba | D7: 120000 | E7: 125
A8: 4 | C8: R Remera boca | D8: 5000 | E8: 5.21
A9: 5 | C9: R Zapatillas nike | D9: 40000 | E9: 41.67
A10: TOTAL INGRESOS | D10: =SUM(D5:D9) | E10: =SUM(E5:E9)
A12: ▼ EGRESOS FIJOS
A13: # | B13: Description | C13: ARS | D13: USD | E13: Status
A14: 1 | B14: HSBC | D14: 275000 | E14: 275 | F14: Pendiente
A15: 2 | B15: Expensas + Estela | D15: 67000 | E15: 67.68
A16: 3 | B16: Gali Prestamo | D16: 15500 | E16: 15.66 | F16: Pagado
A17: TOTAL FIJOS | D17: =SUM(D14:D16) | E17: =SUM(E14:E16)
A19: 📋 GASTOS DEL MES
A20: # | B20: Date | C20: Description | D20: ARS | E20: USD | F20: Category | G20: Payment
A21: 1 | B21: 01 | C21: Remera Real Madrid | D21: 8500 | E21: 8.85
A22: 2 | B22: 02 | C22: Non Parei 1kg | D22: 7000 | E22: 7.29
A23: 3 | B23: 03 | C23: Comida x2 | D23: 4000 | E23: 4.17
A24: 4 | B24: 05 | C24: Pizza | D24: 3500 | E24: 3.65
A25: 5 | B25: 08 | C25: Sanguche | D25: 2500 | E25: 2.6
A26: 6 | B26: 12 | C26: Kiosco | D26: 3000 | E26: 3.13
A27: 7 | B27: 15 | C27: Almuerzo | D27: 5000 | E27: 5.21
A46: TOTAL VARIABLE | D46: =SUM(D21:D45) | E46: =SUM(E21:E45)
A48: 💰 BALANCE | D48: =D10-D17-D46 | E48: =E10-E17-E46

Sheet Dec 2023
A1: 💸 DEC 2023 — GASTOS MENSUALES
A2: USD/ARS | B2: 960 | C2: ← update monthly
A3: ▲ INGRESOS
A4: # | B4: Source | C4: Description | D4: ARS | E4: USD
A5: 1 | C5: D Dani | D5: 500000 | E5: 500
A6: 2 | C6: A Airbnb | D6: 50000 | E6: 50
A7: 3 | C7: A BETA 11 al 15 | D7: 140000 | E7: 140
A8: TOTAL INGRESOS | D8: =SUM(D5:D7) | E8: =SUM(E5:E7)
A10: ▼ EGRESOS FIJOS
A11: # | B11: Description | C11: ARS | D11: USD | E11: Status
A12: 1 | B12: HSBC | D12: 275000 | E12: 275
A13: 2 | B13: Expensas + Estela | D13: 67000 | E13: 67.68
A14: 3 | B14: Gali Prestamo | D14: 15500 | E14: 15.66
A15: TOTAL FIJOS | D15: =SUM(D12:D14) | E15: =SUM(E12:E14)
A17: 📋 GASTOS DEL MES
A18: # | B18: Date | C18: Description | D18: ARS | E18: USD | F18: Category | G18: Payment
A19: 1 | B19: 01 | C19: Didi cumple pen | D19: 2500 | E19: 2.6
A20: 2 | B20: 02 | C20: Sang Vacio | D20: 3000 | E20: 3.12
A21: 3 | B21: 03 | C21: Emp Crazy che | D21: 3200 | E21: 3.33
A22: 4 | B22: 05 | C22: Kiosco | D22: 2000 | E22: 2.08
A23: 5 | B23: 10 | C23: Comida x2 | D23: 8000 | E23: 8.33
A24: 6 | B24: 15 | C24: Almuerzo | D24: 5000 | E24: 5.21
A25: 7 | B25: 20 | C25: Cerveza | D25: 3000 | E25: 3.12
A44: TOTAL VARIABLE | D44: =SUM(D19:D43) | E44: =SUM(E19:E43)
A46: 💰 BALANCE | D46: =D8-D15-D44 | E46: =E8-E15-E44

Sheet Jan 2024
A1: 💸 JAN 2024 — GASTOS MENSUALES
A2: USD/ARS | B2: 1150 | C2: ← update monthly
A3: ▲ INGRESOS
A4: # | B4: Source | C4: Description | D4: ARS | E4: USD
A5: 1 | C5: R Mochila Columbia | D5: 70000 | E5: 70
A6: 2 | C6: R Remera Real Madrid | D6: 25000 | E6: 21.74
A7: 3 | C7: R Hamburgo | D7: 22000 | E7: 19.13
A8: TOTAL INGRESOS | D8: =SUM(D5:D7) | E8: =SUM(E5:E7)
A10: ▼ EGRESOS FIJOS
A11: # | B11: Description | C11: ARS | D11: USD | E11: Status
A12: 1 | B12: HSBC | D12: 200000 | E12: 202.02
A13: 2 | B13: Expensas + Estela | D13: 99000 | E13: 99
A14: 3 | B14: Gali Prestamo | D14: 15500 | E14: 15.66
A15: TOTAL FIJOS | D15: =SUM(D12:D14) | E15: =SUM(E12:E14)
A17: 📋 GASTOS DEL MES
A18: # | B18: Date | C18: Description | D18: ARS | E18: USD | F18: Category | G18: Payment
A19: 1 | B19: 01 | C19: Didi cumple pen | D19: 2500 | E19: 2.17
A20: 2 | B20: 02 | C20: Frutas | D20: 8000 | E20: 6.96
A21: 3 | B21: 04 | C21: Corchio | D21: 6000 | E21: 5.22
A44: TOTAL VARIABLE | D44: =SUM(D19:D43) | E44: =SUM(E19:E43)
A46: 💰 BALANCE | D46: =D8-D15-D44 | E46: =E8-E15-E44

Sheet Feb 2024
A1: 💸 FEB 2024 — GASTOS MENSUALES
A2: USD/ARS | B2: 1150 | C2: ← update monthly
A3: ▲ INGRESOS
A4: # | B4: Source | C4: Description | D4: ARS | E4: USD
A5: 1 | C5: 2 catta Valen | D5: 65000 | E5: 56.52
A6: 2 | C6: 1 publi Feba | D6: 20000 | E6: 17.39
A7: TOTAL INGRESOS | D7: =SUM(D5:D6) | E7: =SUM(E5:E6)
A9: ▼ EGRESOS FIJOS
A10: # | B10: Description | C10: ARS | D10: USD | E10: Status
A11: 1 | B11: HSBC | D11: 200000 | E11: 202.02
A12: 2 | B12: Gali Prestamo | D12: 15500 | E12: 15.66
A13: 3 | B13: Rentas | D13: 6000 | E13: 6.06
A14: TOTAL FIJOS | D14: =SUM(D11:D13) | E14: =SUM(E11:E13)
A16: 📋 GASTOS DEL MES
A17: # | B17: Date | C17: Description | D17: ARS | E17: USD | F17: Category | G17: Payment
A18: 1 | B18: 01 | C18: Chip E-sim | D18: 2500 | E18: 2.17
A43: TOTAL VARIABLE | D43: =SUM(D18:D42) | E43: =SUM(E18:E42)
A45: 💰 BALANCE | D45: =D7-D14-D43 | E45: =E7-E14-E43

Sheet Mar 2024
A1: 💸 MAR 2024 — GASTOS MENSUALES
A2: USD/ARS | B2: 1 | C2: ← update monthly
A3: ▲ INGRESOS
A4: # | B4: Source | C4: Description | D4: ARS | E4: USD
A5: 1 | C5: AirbnbGift | E5: 160
A6: 2 | C6: Amazon Marcel | E6: 332
A7: 3 | C7: Jattin | E7: 26
A8: 4 | C8: Helpling Horas | E8: 270
A9: TOTAL INGRESOS | D9: =SUM(D5:D8) | E9: =SUM(E5:E8)
A11: ▼ EGRESOS FIJOS
A12: # | B12: Description | C12: ARS | D12: USD | E12: Status
A13: 1 | B13: BBVA VISA | E13: 3500
A14: 2 | B14: BBVA MCARD | E14: 4700
A15: 3 | B15: Monotrib | E15: 11000
A16: TOTAL FIJOS | D16: =SUM(D13:D15) | E16: =SUM(E13:E15)
A18: 📋 GASTOS DEL MES
A19: # | B19: Date | C19: Description | D19: ARS | E19: USD | F19: Category | G19: Payment
A20: 1 | B20: 09 | C20: Bolt | E20: 11
A21: 2 | B21: 10 | C21: O2 Recarga | E21: 15
A22: 3 | B22: 11 | C22: Anmeldung | E22: 40
A23: 4 | B23: 12 | C23: DB Tickets | E23: 28
A24: 5 | B24: 15 | C24: Supermercado | E24: 45
A45: TOTAL VARIABLE | D45: =SUM(D20:D44) | E45: =SUM(E20:E44)
A47: 💰 BALANCE | D47: =D9-D16-D45 | E47: =E9-E16-E45

Sheet Apr 2024
A1: 💸 APR 2024 — GASTOS MENSUALES
A2: USD/ARS | B2: 1 | C2: ← update monthly
A3: ▲ INGRESOS
A4: # | B4: Source | C4: Description | D4: ARS | E4: USD
A5: 1 | C5: Andalucia Propi | E5: 110
A6: 2 | C6: Helpling Abril | E6: 684
A7: TOTAL INGRESOS | D7: =SUM(D5:D6) | E7: =SUM(E5:E6)
A9: ▼ EGRESOS FIJOS
A10: # | B10: Description | C10: ARS | D10: USD | E10: Status
A11: 1 | B11: Monotrib | E11: 11000
A12: 2 | B12: BBVA VISA | E12: 3500
A13: 3 | B13: BBVA MCARD | E13: 4700
A14: TOTAL FIJOS | D14: =SUM(D11:D13) | E14: =SUM(E11:E13)
A16: 📋 GASTOS DEL MES
A17: # | B17: Date | C17: Description | D17: ARS | E17: USD | F17: Category | G17: Payment
A43: TOTAL VARIABLE | D43: =SUM(D18:D42) | E43: =SUM(E18:E42)
A45: 💰 BALANCE | D45: =D7-D14-D43 | E45: =E7-E14-E43

Sheet May 2024
A1: 💸 MAY 2024 — GASTOS MENSUALES
A2: USD/ARS | B2: 1 | C2: ← update monthly
A3: ▲ INGRESOS
A4: # | B4: Source | C4: Description | D4: ARS | E4: USD
A5: 1 | C5: Hellpling Ramona | E5: 25
A6: 2 | C6: Bici SP blanca | E6: 145
A7: 3 | C7: Bici Sp Elops | E7: 120
A8: 4 | C8: Amazon Helpling | E8: 200
A9: TOTAL INGRESOS | D9: =SUM(D5:D8) | E9: =SUM(E5:E8)
A11: ▼ EGRESOS FIJOS
A12: # | B12: Description | C12: ARS | D12: USD | E12: Status
A13: 1 | B13: DAK | E13: 300
A14: 2 | B14: Monotrib | E14: 11000
A15: 3 | B15: Exp Arenales | E15: 42000
A16: TOTAL FIJOS | D16: =SUM(D13:D15) | E16: =SUM(E13:E15)
A18: 📋 GASTOS DEL MES
A19: # | B19: Date | C19: Description | D19: ARS | E19: USD | F19: Category | G19: Payment
A45: TOTAL VARIABLE | D45: =SUM(D20:D44) | E45: =SUM(E20:E44)
A47: 💰 BALANCE | D47: =D9-D16-D45 | E47: =E9-E16-E45

Sheet Jun 2024
A1: 💸 JUN 2024 — GASTOS MENSUALES
A2: USD/ARS | B2: 1 | C2: ← update monthly
A3: ▲ INGRESOS
A4: # | B4: Source | C4: Description | D4: ARS | E4: USD
A5: TOTAL INGRESOS | D5: =SUM(D5:D4) | E5: =SUM(E5:E4)
A7: ▼ EGRESOS FIJOS
A8: # | B8: Description | C8: ARS | D8: USD | E8: Status
A9: TOTAL FIJOS | D9: =SUM(D9:D8) | E9: =SUM(E9:E8)
A11: 📋 GASTOS DEL MES
A12: # | B12: Date | C12: Description | D12: ARS | E12: USD | F12: Category | G12: Payment
A13: 1 | B13: 02 | C13: Cash USD | E13: 200
A14: 2 | B14: 03 | C14: Payo USD | E14: 380
A15: 3 | B15: 04 | C15: Revolut | E15: 108
A16: 4 | B16: 10 | C16: Comida | E16: 35
A17: 5 | B17: 15 | C17: Transport | E17: 25
A38: TOTAL VARIABLE | D38: =SUM(D13:D37) | E38: =SUM(E13:E37)
A40: 💰 BALANCE | D40: =D5-D9-D38 | E40: =E5-E9-E38

Sheet Jul 2024
A1: 💸 JUL 2024 — GASTOS MENSUALES
A2: USD/ARS | B2: 1 | C2: ← update monthly
A3: ▲ INGRESOS
A4: # | B4: Source | C4: Description | D4: ARS | E4: USD
A5: TOTAL INGRESOS | D5: =SUM(D5:D4) | E5: =SUM(E5:E4)
A7: ▼ EGRESOS FIJOS
A8: # | B8: Description | C8: ARS | D8: USD | E8: Status
A9: TOTAL FIJOS | D9: =SUM(D9:D8) | E9: =SUM(E9:E8)
A11: 📋 GASTOS DEL MES
A12: # | B12: Date | C12: Description | D12: ARS | E12: USD | F12: Category | G12: Payment
A13: 1 | B13: 08 | C13: Burrito | E13: 10
A14: 2 | B14: 09 | C14: Pizza | E14: 8
A15: 3 | B15: 10 | C15: Kebab | E15: 12
A16: 4 | B16: 15 | C16: Supermercado | E16: 45
A17: 5 | B17: 20 | C17: Transporte | E17: 18
A38: TOTAL VARIABLE | D38: =SUM(D13:D37) | E38: =SUM(E13:E37)
A40: 💰 BALANCE | D40: =D5-D9-D38 | E40: =E5-E9-E38

Sheet Aug 2024
A1: 💸 AUG 2024 — GASTOS MENSUALES
A2: USD/ARS | B2: 1 | C2: ← update monthly
A3: ▲ INGRESOS
A4: # | B4: Source | C4: Description | D4: ARS | E4: USD
A5: TOTAL INGRESOS | D5: =SUM(D5:D4) | E5: =SUM(E5:E4)
A7: ▼ EGRESOS FIJOS
A8: # | B8: Description | C8: ARS | D8: USD | E8: Status
A9: TOTAL FIJOS | D9: =SUM(D9:D8) | E9: =SUM(E9:E8)
A11: 📋 GASTOS DEL MES
A12: # | B12: Date | C12: Description | D12: ARS | E12: USD | F12: Category | G12: Payment
A13: 1 | B13: 01 | C13: Comida | E13: 30
A14: 2 | B14: 05 | C14: Transporte | E14: 20
A15: 3 | B15: 10 | C15: Supermercado | E15: 55
A16: 4 | B16: 15 | C16: Restaurante | E16: 35
A17: 5 | B17: 20 | C17: Misc | E17: 25
A38: TOTAL VARIABLE | D38: =SUM(D13:D37) | E38: =SUM(E13:E37)
A40: 💰 BALANCE | D40: =D5-D9-D38 | E40: =E5-E9-E38

Sheet Sep 2024
A1: 💸 SEP 2024 — GASTOS MENSUALES
A2: USD/ARS | B2: 1 | C2: ← update monthly
A3: ▲ INGRESOS
A4: # | B4: Source | C4: Description | D4: ARS | E4: USD
A5: TOTAL INGRESOS | D5: =SUM(D5:D4) | E5: =SUM(E5:E4)
A7: ▼ EGRESOS FIJOS
A8: # | B8: Description | C8: ARS | D8: USD | E8: Status
A9: TOTAL FIJOS | D9: =SUM(D9:D8) | E9: =SUM(E9:E8)
A11: 📋 GASTOS DEL MES
A12: # | B12: Date | C12: Description | D12: ARS | E12: USD | F12: Category | G12: Payment
A13: 1 | B13: 02 | C13: Calzoni | E13: 8
A14: 2 | B14: 03 | C14: Pizza | E14: 6
A15: 3 | B15: 05 | C15: Remeras HM | E15: 20
A16: 4 | B16: 10 | C16: Supermercado | E16: 40
A17: 5 | B17: 15 | C17: Transporte | E17: 15
A38: TOTAL VARIABLE | D38: =SUM(D13:D37) | E38: =SUM(E13:E37)
A40: 💰 BALANCE | D40: =D5-D9-D38 | E40: =E5-E9-E38

Sheet Oct 2024
A1: 💸 OCT 2024 — GASTOS MENSUALES
A2: USD/ARS | B2: 1 | C2: ← update monthly
A3: ▲ INGRESOS
A4: # | B4: Source | C4: Description | D4: ARS | E4: USD
A5: TOTAL INGRESOS | D5: =SUM(D5:D4) | E5: =SUM(E5:E4)
A7: ▼ EGRESOS FIJOS
A8: # | B8: Description | C8: ARS | D8: USD | E8: Status
A9: TOTAL FIJOS | D9: =SUM(D9:D8) | E9: =SUM(E9:E8)
A11: 📋 GASTOS DEL MES
A12: # | B12: Date | C12: Description | D12: ARS | E12: USD | F12: Category | G12: Payment
A13: 1 | B13: 04 | C13: Yerba | E13: 8
A14: 2 | B14: 06 | C14: Nachos y hummus | E14: 9
A15: 3 | B15: 07 | C15: Pizza Mercadona | E15: 6
A16: 4 | B16: 15 | C16: Supermercado | E16: 38
A17: 5 | B17: 20 | C17: Misc | E17: 20
A38: TOTAL VARIABLE | D38: =SUM(D13:D37) | E38: =SUM(E13:E37)
A40: 💰 BALANCE | D40: =D5-D9-D38 | E40: =E5-E9-E38

Sheet Nov 2024
A1: 💸 NOV 2024 — GASTOS MENSUALES
A2: USD/ARS | B2: 1200 | C2: ← update monthly
A3: ▲ INGRESOS
A4: # | B4: Source | C4: Description | D4: ARS | E4: USD
A5: TOTAL INGRESOS | D5: =SUM(D5:D4) | E5: =SUM(E5:E4)
A7: ▼ EGRESOS FIJOS
A8: # | B8: Description | C8: ARS | D8: USD | E8: Status
A9: TOTAL FIJOS | D9: =SUM(D9:D8) | E9: =SUM(E9:E8)
A11: 📋 GASTOS DEL MES
A12: # | B12: Date | C12: Description | D12: ARS | E12: USD | F12: Category | G12: Payment
A13: 1 | B13: 16 | C13: Psico | E13: 15
A14: 2 | B14: 18 | C14: SUBE | D14: 5000 | E14: =IF(D14>0,D14/B$2,"")
A15: 3 | B15: 19 | C15: Didi a ver a los bull | D15: 5590 | E15: =IF(D15>0,D15/B$2,"")
A16: 4 | B16: 20 | C16: Almuerzo | D16: 3000 | E16: =IF(D16>0,D16/B$2,"")
A17: 5 | B17: 25 | C17: Comida | D17: 4000 | E17: =IF(D17>0,D17/B$2,"")
A38: TOTAL VARIABLE | D38: =SUM(D13:D37) | E38: =SUM(E13:E37)
A40: 💰 BALANCE | D40: =D5-D9-D38 | E40: =E5-E9-E38

Sheet Dec 2024
A1: 💸 DEC 2024 — GASTOS MENSUALES
A2: USD/ARS | B2: 1200 | C2: ← update monthly
A3: ▲ INGRESOS
A4: # | B4: Source | C4: Description | D4: ARS | E4: USD
A5: TOTAL INGRESOS | D5: =SUM(D5:D4) | E5: =SUM(E5:E4)
A7: ▼ EGRESOS FIJOS
A8: # | B8: Description | C8: ARS | D8: USD | E8: Status
A9: TOTAL FIJOS | D9: =SUM(D9:D8) | E9: =SUM(E9:E8)
A11: 📋 GASTOS DEL MES
A12: # | B12: Date | C12: Description | D12: ARS | E12: USD | F12: Category | G12: Payment
A13: 1 | B13: 11 | C13: Sanguche | D13: 7500 | E13: =IF(D13>0,D13/B$2,"")
A14: 2 | B14: 12 | C14: Tognis FIFA | D14: 15000 | E14: =IF(D14>0,D14/B$2,"")
A15: 3 | B15: 13 | C15: Didi FIFA | D15: 10000 | E15: =IF(D15>0,D15/B$2,"")
A16: 4 | B16: 14 | C16: Comida | D16: 5000 | E16: =IF(D16>0,D16/B$2,"")
A17: 5 | B17: 20 | C17: Kiosco | D17: 3000 | E17: =IF(D17>0,D17/B$2,"")
A38: TOTAL VARIABLE | D38: =SUM(D13:D37) | E38: =SUM(E13:E37)
A40: 💰 BALANCE | D40: =D5-D9-D38 | E40: =E5-E9-E38

Sheet Jan 2025
A1: 💸 JAN 2025 — GASTOS MENSUALES
A2: USD/ARS | B2: 1100 | C2: ← update monthly
A3: ▲ INGRESOS
A4: # | B4: Source | C4: Description | D4: ARS | E4: USD
A5: TOTAL INGRESOS | D5: =SUM(D5:D4) | E5: =SUM(E5:E4)
A7: ▼ EGRESOS FIJOS
A8: # | B8: Description | C8: ARS | D8: USD | E8: Status
A9: TOTAL FIJOS | D9: =SUM(D9:D8) | E9: =SUM(E9:E8)
A11: 📋 GASTOS DEL MES
A12: # | B12: Date | C12: Description | D12: ARS | E12: USD | F12: Category | G12: Payment
A13: 1 | B13: 02 | C13: Rapanui | D13: 6000 | E13: =IF(D13>0,D13/B$2,"")
A14: 2 | B14: 03 | C14: Didi | D14: 4800 | E14: =IF(D14>0,D14/B$2,"")
A15: 3 | B15: 04 | C15: Echeverria pasaje | D15: 14000 | E15: =IF(D15>0,D15/B$2,"")
A16: 4 | B16: 05 | C16: Comida | D16: 8000 | E16: =IF(D16>0,D16/B$2,"")
A17: 5 | B17: 10 | C17: Almuerzo | D17: 5000 | E17: =IF(D17>0,D17/B$2,"")
A38: TOTAL VARIABLE | D38: =SUM(D13:D37) | E38: =SUM(E13:E37)
A40: 💰 BALANCE | D40: =D5-D9-D38 | E40: =E5-E9-E38

Sheet Feb 2025
A1: 💸 FEB 2025 — GASTOS MENSUALES
A2: USD/ARS | B2: 1100 | C2: ← update monthly
A3: ▲ INGRESOS
A4: # | B4: Source | C4: Description | D4: ARS | E4: USD
A5: TOTAL INGRESOS | D5: =SUM(D5:D4) | E5: =SUM(E5:E4)
A7: ▼ EGRESOS FIJOS
A8: # | B8: Description | C8: ARS | D8: USD | E8: Status
A9: TOTAL FIJOS | D9: =SUM(D9:D8) | E9: =SUM(E9:E8)
A11: 📋 GASTOS DEL MES
A12: # | B12: Date | C12: Description | D12: ARS | E12: USD | F12: Category | G12: Payment
A38: TOTAL VARIABLE | D38: =SUM(D13:D37) | E38: =SUM(E13:E37)
A40: 💰 BALANCE | D40: =D5-D9-D38 | E40: =E5-E9-E38

Sheet Mar 2025
A1: 💸 MAR 2025 — GASTOS MENSUALES
A2: USD/ARS | B2: 1000 | C2: ← update monthly
A3: ▲ INGRESOS
A4: # | B4: Source | C4: Description | D4: ARS | E4: USD
A5: 1 | C5: Basecoat | E5: 933
A6: 2 | C6: Bono Compu Basecoat | E6: 500
A7: 3 | C7: Basecoat 2 | E7: 963
A8: 4 | C8: Mati sun | E8: 65
A9: 5 | C9: Fiesta Maru Bo | E9: 65
A10: 6 | C10: Grego Dj | E10: 25
A11: TOTAL INGRESOS | D11: =SUM(D5:D10) | E11: =SUM(E5:E10)
A13: ▼ EGRESOS FIJOS
A14: # | B14: Description | C14: ARS | D14: USD | E14: Status
A15: 1 | B15: MSI Cyborg | E15: 810
A16: 2 | B16: Asisa Seguro | E16: 45
A17: 3 | B17: Sillon | D17: 230000 | E17: =IF(D17>0,D17/B$2,"")
A18: 4 | B18: Monitor | D18: 250000 | E18: =IF(D18>0,D18/B$2,"")
A19: 5 | B19: AGIP
A20: 6 | B20: Exp Arenales
A21: 7 | B21: AYSA Arenales
A22: 8 | B22: Luz Edesur
A23: 9 | B23: Gas Arenales
A24: 10 | B24: Telecentro
A25: TOTAL FIJOS | D25: =SUM(D15:D24) | E25: =SUM(E15:E24)
A27: 📋 GASTOS DEL MES
A28: # | B28: Date | C28: Description | D28: ARS | E28: USD | F28: Category | G28: Payment
A54: TOTAL VARIABLE | D54: =SUM(D29:D53) | E54: =SUM(E29:E53)
A56: 💰 BALANCE | D56: =D11-D25-D54 | E56: =E11-E25-E54

Sheet Apr 2025
A1: 💸 APR 2025 — GASTOS MENSUALES
A2: USD/ARS | B2: 1000 | C2: ← update monthly
A3: ▲ INGRESOS
A4: # | B4: Source | C4: Description | D4: ARS | E4: USD
A5: 1 | C5: Basecoat | E5: 880
A6: 2 | C6: Basecoat 2 | E6: 963
A7: 3 | C7: Mati sun | E7: 65
A8: 4 | C8: Fiesta Maru Bo | E8: 65
A9: 5 | C9: Grego Dj | E9: 25
A10: TOTAL INGRESOS | D10: =SUM(D5:D9) | E10: =SUM(E5:E9)
A12: ▼ EGRESOS FIJOS
A13: # | B13: Description | C13: ARS | D13: USD | E13: Status
A14: 1 | B14: Swiss | D14: 150000 | E14: =IF(D14>0,D14/B$2,"")
A15: 2 | B15: Telecentro | D15: 36000 | E15: =IF(D15>0,D15/B$2,"")
A16: 3 | B16: Fonoaudiologo | D16: 20000 | E16: =IF(D16>0,D16/B$2,"")
A17: 4 | B17: Gym | D17: 23000 | E17: =IF(D17>0,D17/B$2,"")
A18: 5 | B18: Asisa | E18: 50
A19: 6 | B19: Santander Esp | E19: 20
A20: 7 | B20: Olav Depto | D20: 100000 | E20: =IF(D20>0,D20/B$2,"")
A21: 8 | B21: Comida Olav | D21: 500000 | E21: =IF(D21>0,D21/B$2,"")
A22: TOTAL FIJOS | D22: =SUM(D14:D21) | E22: =SUM(E14:E21)
A24: 📋 GASTOS DEL MES
A25: # | B25: Date | C25: Description | D25: ARS | E25: USD | F25: Category | G25: Payment
A51: TOTAL VARIABLE | D51: =SUM(D26:D50) | E51: =SUM(E26:E50)
A53: 💰 BALANCE | D53: =D10-D22-D51 | E53: =E10-E22-E51

Sheet May 2025
A1: 💸 MAY 2025 — GASTOS MENSUALES
A2: USD/ARS | B2: 1000 | C2: ← update monthly
A3: ▲ INGRESOS
A4: # | B4: Source | C4: Description | D4: ARS | E4: USD
A5: 1 | C5: Basecoat | E5: 880
A6: 2 | C6: Basecoat 2 | E6: 963
A7: TOTAL INGRESOS | D7: =SUM(D5:D6) | E7: =SUM(E5:E6)
A9: ▼ EGRESOS FIJOS
A10: # | B10: Description | C10: ARS | D10: USD | E10: Status
A11: 1 | B11: Swiss | D11: 150000 | E11: =IF(D11>0,D11/B$2,"")
A12: 2 | B12: Fonoaudiologo | D12: 20000 | E12: =IF(D12>0,D12/B$2,"")
A13: 3 | B13: Gym | D13: 23000 | E13: =IF(D13>0,D13/B$2,"")
A14: 4 | B14: Asisa | E14: 50
A15: 5 | B15: Santander Esp | E15: 20
A16: 6 | B16: Olav Depto | D16: 100000 | E16: =IF(D16>0,D16/B$2,"")
A17: 7 | B17: Comida Olav | D17: 500000 | E17: =IF(D17>0,D17/B$2,"")
A18: 8 | B18: Psico | D18: 30000 | E18: =IF(D18>0,D18/B$2,"")
A19: TOTAL FIJOS | D19: =SUM(D11:D18) | E19: =SUM(E11:E18)
A21: 📋 GASTOS DEL MES
A22: # | B22: Date | C22: Description | D22: ARS | E22: USD | F22: Category | G22: Payment
A23: 1 | B23: 02 | C23: Bizcochos | D23: 5300 | E23: =IF(D23>0,D23/B$2,"")
A24: 2 | B24: 04 | C24: Pietra milanesas | D24: 13400 | E24: =IF(D24>0,D24/B$2,"")
A25: 3 | B25: 05 | C25: Psico mari | D25: 20000 | E25: =IF(D25>0,D25/B$2,"")
A26: 4 | B26: 06 | C26: Psico 2 | D26: 20000 | E26: =IF(D26>0,D26/B$2,"")
A27: 5 | B27: 07 | C27: Psico 3 swiss | D27: 13500 | E27: =IF(D27>0,D27/B$2,"")
A48: TOTAL VARIABLE | D48: =SUM(D23:D47) | E48: =SUM(E23:E47)
A50: 💰 BALANCE | D50: =D7-D19-D48 | E50: =E7-E19-E48

Sheet Jun 2025
A1: 💸 JUN 2025 — GASTOS MENSUALES
A2: USD/ARS | B2: 1100 | C2: ← update monthly
A3: ▲ INGRESOS
A4: # | B4: Source | C4: Description | D4: ARS | E4: USD
A5: 1 | C5: Basecoat | E5: 880
A6: 2 | C6: Basecoat 2 | E6: 963
A7: TOTAL INGRESOS | D7: =SUM(D5:D6) | E7: =SUM(E5:E6)
A9: ▼ EGRESOS FIJOS
A10: # | B10: Description | C10: ARS | D10: USD | E10: Status
A11: 1 | B11: Swiss | D11: 150000 | E11: =IF(D11>0,D11/B$2,"")
A12: 2 | B12: Fonoaudiologo | D12: 20000 | E12: =IF(D12>0,D12/B$2,"")
A13: 3 | B13: Gym | D13: 30000 | E13: =IF(D13>0,D13/B$2,"")
A14: 4 | B14: Asisa | E14: 50
A15: 5 | B15: Santander Esp | E15: 20
A16: 6 | B16: Olav Depto | D16: 100000 | E16: =IF(D16>0,D16/B$2,"")
A17: 7 | B17: Comida Olav | D17: 500000 | E17: =IF(D17>0,D17/B$2,"")
A18: 8 | B18: Psico x4 | D18: 42000 | E18: =IF(D18>0,D18/B$2,"")
A19: TOTAL FIJOS | D19: =SUM(D11:D18) | E19: =SUM(E11:E18)
A21: 📋 GASTOS DEL MES
A22: # | B22: Date | C22: Description | D22: ARS | E22: USD | F22: Category | G22: Payment
A23: 1 | B23: 02 | C23: Bizcochos | D23: 5300 | E23: =IF(D23>0,D23/B$2,"")
A24: 2 | B24: 03 | C24: Crazy cheese | D24: 18000 | E24: =IF(D24>0,D24/B$2,"")
A48: TOTAL VARIABLE | D48: =SUM(D23:D47) | E48: =SUM(E23:E47)
A50: 💰 BALANCE | D50: =D7-D19-D48 | E50: =E7-E19-E48

Sheet Jul 2025
A1: 💸 JUL 2025 — GASTOS MENSUALES
A2: USD/ARS | B2: 1200 | C2: ← update monthly
A3: ▲ INGRESOS
A4: # | B4: Source | C4: Description | D4: ARS | E4: USD
A5: 1 | C5: Ipad Mini Bachi | E5: 100
A6: TOTAL INGRESOS | D6: =SUM(D5:D5) | E6: =SUM(E5:E5)
A8: ▼ EGRESOS FIJOS
A9: # | B9: Description | C9: ARS | D9: USD | E9: Status
A10: 1 | B10: Swiss | D10: 150000 | E10: =IF(D10>0,D10/B$2,"")
A11: 2 | B11: Remedios | D11: 70000 | E11: =IF(D11>0,D11/B$2,"")
A12: 3 | B12: Gym | D12: 30000 | E12: =IF(D12>0,D12/B$2,"")
A13: 4 | B13: Asisa | E13: 50
A14: 5 | B14: Santander Esp | E14: 20
A15: 6 | B15: Olav Depto | D15: 100000 | E15: =IF(D15>0,D15/B$2,"")
A16: 7 | B16: Comida Olav | D16: 500000 | E16: =IF(D16>0,D16/B$2,"")
A17: 8 | B17: Psico x4 | D17: 42000 | E17: =IF(D17>0,D17/B$2,"")
A18: TOTAL FIJOS | D18: =SUM(D10:D17) | E18: =SUM(E10:E17)
A20: 📋 GASTOS DEL MES
A21: # | B21: Date | C21: Description | D21: ARS | E21: USD | F21: Category | G21: Payment
A22: 1 | B22: 02 | C22: Bizcochos | D22: 5300 | E22: =IF(D22>0,D22/B$2,"")
A23: 2 | B23: 03 | C23: Crazy cheese | D23: 18000 | E23: =IF(D23>0,D23/B$2,"")
A24: 3 | B24: 04 | C24: Auto Fabi | D24: 30000 | E24: =IF(D24>0,D24/B$2,"")
A25: 4 | B25: 05 | C25: Empanadas | D25: 45000 | E25: =IF(D25>0,D25/B$2,"")
A26: 5 | B26: 07 | C26: Strange | D26: 30000 | E26: =IF(D26>0,D26/B$2,"")
A47: TOTAL VARIABLE | D47: =SUM(D22:D46) | E47: =SUM(E22:E46)
A49: 💰 BALANCE | D49: =D6-D18-D47 | E49: =E6-E18-E47

Sheet Aug 2025
A1: 💸 AUG 2025 — GASTOS MENSUALES
A2: USD/ARS | B2: 1300 | C2: ← update monthly
A3: ▲ INGRESOS
A4: # | B4: Source | C4: Description | D4: ARS | E4: USD
A5: TOTAL INGRESOS | D5: =SUM(D5:D4) | E5: =SUM(E5:E4)
A7: ▼ EGRESOS FIJOS
A8: # | B8: Description | C8: ARS | D8: USD | E8: Status
A9: 1 | B9: Swiss | D9: 150000 | E9: =IF(D9>0,D9/B$2,"")
A10: 2 | B10: Remedios | D10: 30000 | E10: =IF(D10>0,D10/B$2,"")
A11: 3 | B11: Gym | D11: 30000 | E11: =IF(D11>0,D11/B$2,"")
A12: 4 | B12: Asisa | D12: 50000 | E12: =IF(D12>0,D12/B$2,"")
A13: 5 | B13: Santander Esp | D13: 20000 | E13: =IF(D13>0,D13/B$2,"")
A14: 6 | B14: Olav Depto | D14: 130000 | E14: =IF(D14>0,D14/B$2,"")
A15: 7 | B15: Comida Olav | D15: 800000 | E15: =IF(D15>0,D15/B$2,"")
A16: 8 | B16: Psico x2 | D16: 33000 | E16: =IF(D16>0,D16/B$2,"")
A17: 9 | B17: Escribano | D17: 30000 | E17: =IF(D17>0,D17/B$2,"")
A18: 10 | B18: Internet | D18: 20000 | E18: =IF(D18>0,D18/B$2,"")
A19: TOTAL FIJOS | D19: =SUM(D9:D18) | E19: =SUM(E9:E18)
A21: 📋 GASTOS DEL MES
A22: # | B22: Date | C22: Description | D22: ARS | E22: USD | F22: Category | G22: Payment
A23: 1 | B23: 02 | C23: Bizcochos | D23: 5300 | E23: =IF(D23>0,D23/B$2,"")
A24: 2 | B24: 04 | C24: Auto Fabi | D24: 30000 | E24: =IF(D24>0,D24/B$2,"")
A25: 3 | B25: 05 | C25: Empanadas | D25: 45000 | E25: =IF(D25>0,D25/B$2,"")
A48: TOTAL VARIABLE | D48: =SUM(D23:D47) | E48: =SUM(E23:E47)
A50: 💰 BALANCE | D50: =D5-D19-D48 | E50: =E5-E19-E48

Sheet Sep 2025
A1: 💸 SEP 2025 — GASTOS MENSUALES
A2: USD/ARS | B2: 1400 | C2: ← update monthly
A3: ▲ INGRESOS
A4: # | B4: Source | C4: Description | D4: ARS | E4: USD
A5: TOTAL INGRESOS | D5: =SUM(D5:D4) | E5: =SUM(E5:E4)
A7: ▼ EGRESOS FIJOS
A8: # | B8: Description | C8: ARS | D8: USD | E8: Status
A9: 1 | B9: Swiss | D9: 150000 | E9: =IF(D9>0,D9/B$2,"")
A10: 2 | B10: Olav Depto | D10: 100000 | E10: =IF(D10>0,D10/B$2,"")
A11: 3 | B11: Gym+Cal | D11: 37000 | E11: =IF(D11>0,D11/B$2,"")
A12: 4 | B12: Asisa | D12: 50000 | E12: =IF(D12>0,D12/B$2,"")
A13: 5 | B13: Santander Esp | D13: 20000 | E13: =IF(D13>0,D13/B$2,"")
A14: 6 | B14: Psico | D14: 16000 | E14: =IF(D14>0,D14/B$2,"")
A15: 7 | B15: Comida Olav | D15: 600000 | E15: =IF(D15>0,D15/B$2,"")
A16: TOTAL FIJOS | D16: =SUM(D9:D15) | E16: =SUM(E9:E15)
A18: 📋 GASTOS DEL MES
A19: # | B19: Date | C19: Description | D19: ARS | E19: USD | F19: Category | G19: Payment
A20: 1 | B20: 08 | C20: Reme Patagonia | D20: 43000 | E20: =IF(D20>0,D20/B$2,"")
A21: 2 | B21: 15 | C21: Havana | D21: 50000 | E21: =IF(D21>0,D21/B$2,"")
A45: TOTAL VARIABLE | D45: =SUM(D20:D44) | E45: =SUM(E20:E44)
A47: 💰 BALANCE | D47: =D5-D16-D45 | E47: =E5-E16-E45

Sheet Oct 2025
A1: 💸 OCT 2025 — GASTOS MENSUALES
A2: USD/ARS | B2: 1450 | C2: ← update monthly
A3: ▲ INGRESOS
A4: # | B4: Source | C4: Description | D4: ARS | E4: USD
A5: TOTAL INGRESOS | D5: =SUM(D5:D4) | E5: =SUM(E5:E4)
A7: ▼ EGRESOS FIJOS
A8: # | B8: Description | C8: ARS | D8: USD | E8: Status
A9: 1 | B9: Swiss | D9: 165000 | E9: =IF(D9>0,D9/B$2,"")
A10: 2 | B10: Olav Depto | D10: 100000 | E10: =IF(D10>0,D10/B$2,"")
A11: 3 | B11: Endomedicame | D11: 50000 | E11: =IF(D11>0,D11/B$2,"")
A12: 4 | B12: Gym | D12: 37000 | E12: =IF(D12>0,D12/B$2,"")
A13: 5 | B13: Asisa | D13: 50000 | E13: =IF(D13>0,D13/B$2,"")
A14: 6 | B14: Santander Esp | D14: 20000 | E14: =IF(D14>0,D14/B$2,"")
A15: 7 | B15: Psico | D15: 16000 | E15: =IF(D15>0,D15/B$2,"")
A16: 8 | B16: Comida Olav | D16: 600000 | E16: =IF(D16>0,D16/B$2,"")
A17: TOTAL FIJOS | D17: =SUM(D9:D16) | E17: =SUM(E9:E16)
A19: 📋 GASTOS DEL MES
A20: # | B20: Date | C20: Description | D20: ARS | E20: USD | F20: Category | G20: Payment
A46: TOTAL VARIABLE | D46: =SUM(D21:D45) | E46: =SUM(E21:E45)
A48: 💰 BALANCE | D48: =D5-D17-D46 | E48: =E5-E17-E46

Sheet Nov 2025
A1: 💸 NOV 2025 — GASTOS MENSUALES
A2: USD/ARS | B2: 1450 | C2: ← update monthly
A3: ▲ INGRESOS
A4: # | B4: Source | C4: Description | D4: ARS | E4: USD
A5: TOTAL INGRESOS | D5: =SUM(D5:D4) | E5: =SUM(E5:E4)
A7: ▼ EGRESOS FIJOS
A8: # | B8: Description | C8: ARS | D8: USD | E8: Status
A9: 1 | B9: Comida y mas | D9: 900000 | E9: =IF(D9>0,D9/B$2,"")
A10: 2 | B10: Swiss | D10: 165000 | E10: =IF(D10>0,D10/B$2,"")
A11: 3 | B11: Olav Depto | D11: 100000 | E11: =IF(D11>0,D11/B$2,"")
A12: 4 | B12: Pilates | D12: 43000 | E12: =IF(D12>0,D12/B$2,"")
A13: 5 | B13: Gym | D13: 34000 | E13: =IF(D13>0,D13/B$2,"")
A14: 6 | B14: Asisa | D14: 50000 | E14: =IF(D14>0,D14/B$2,"")
A15: 7 | B15: Santander Esp | D15: 20000 | E15: =IF(D15>0,D15/B$2,"")
A16: 8 | B16: Psico | D16: 16000 | E16: =IF(D16>0,D16/B$2,"")
A17: 9 | B17: Tenis | D17: 23000 | E17: =IF(D17>0,D17/B$2,"")
A18: 10 | B18: Internet | D18: 13748 | E18: =IF(D18>0,D18/B$2,"")
A19: 11 | B19: Regalo Guido | D19: 150000 | E19: =IF(D19>0,D19/B$2,"")
A20: 12 | B20: Chapa | D20: 250000 | E20: =IF(D20>0,D20/B$2,"")
A21: 13 | B21: Sur Pesca | D21: 350000 | E21: =IF(D21>0,D21/B$2,"")
A22: TOTAL FIJOS | D22: =SUM(D9:D21) | E22: =SUM(E9:E21)
A24: 📋 GASTOS DEL MES
A25: # | B25: Date | C25: Description | D25: ARS | E25: USD | F25: Category | G25: Payment
A51: TOTAL VARIABLE | D51: =SUM(D26:D50) | E51: =SUM(E26:E50)
A53: 💰 BALANCE | D53: =D5-D22-D51 | E53: =E5-E22-E51

Sheet Dec 2025
A1: 💸 DEC 2025 — GASTOS MENSUALES
A2: USD/ARS | B2: 1500 | C2: ← update monthly
A3: ▲ INGRESOS
A4: # | B4: Source | C4: Description | D4: ARS | E4: USD
A5: 1 | C5: Basecoat | E5: 2750
A6: TOTAL INGRESOS | D6: =SUM(D5:D5) | E6: =SUM(E5:E5)
A8: ▼ EGRESOS FIJOS
A9: # | B9: Description | C9: ARS | D9: USD | E9: Status
A10: 1 | B10: Comida y mas | D10: 900000 | E10: =IF(D10>0,D10/B$2,"")
A11: 2 | B11: Swiss Dic | D11: 172000 | E11: =IF(D11>0,D11/B$2,"")
A12: 3 | B12: Olav Depto | D12: 150000 | E12: =IF(D12>0,D12/B$2,"")
A13: 4 | B13: Gym | D13: 34000 | E13: =IF(D13>0,D13/B$2,"")
A14: 5 | B14: Psico Anab | D14: 30000 | E14: =IF(D14>0,D14/B$2,"")
A15: 6 | B15: Santander Esp | D15: 20000 | E15: =IF(D15>0,D15/B$2,"")
A16: 7 | B16: Tenis | D16: 23000 | E16: =IF(D16>0,D16/B$2,"")
A17: 8 | B17: Internet | D17: 13748 | E17: =IF(D17>0,D17/B$2,"")
A18: TOTAL FIJOS | D18: =SUM(D10:D17) | E18: =SUM(E10:E17)
A20: 📋 GASTOS DEL MES
A21: # | B21: Date | C21: Description | D21: ARS | E21: USD | F21: Category | G21: Payment
A47: TOTAL VARIABLE | D47: =SUM(D22:D46) | E47: =SUM(E22:E46)
A49: 💰 BALANCE | D49: =D6-D18-D47 | E49: =E6-E18-E47

Sheet Jan 2026
A1: 💸 JAN 2026 — GASTOS MENSUALES
A2: USD/ARS | B2: 1500 | C2: ← update monthly
A3: ▲ INGRESOS
A4: # | B4: Source | C4: Description | D4: ARS | E4: USD
A5: 1 | C5: Basecoat | D5: 4500000 | E5: 3000
A6: TOTAL INGRESOS | D6: =SUM(D5:D5) | E6: =SUM(E5:E5)
A8: ▼ EGRESOS FIJOS
A9: # | B9: Description | C9: ARS | D9: USD | E9: Status
A10: 1 | B10: Comida y mas | D10: 900000 | E10: 600
A11: 2 | B11: Swiss Dic | D11: 172000 | E11: 114.67
A12: 3 | B12: Olav Depto | D12: 150000 | E12: 100
A13: 4 | B13: Gym | D13: 34000 | E13: 22.67
A14: 5 | B14: Psico Anab | D14: 30000 | E14: 20
A15: 6 | B15: Santander Esp | D15: 20000 | E15: 13.33
A16: 7 | B16: Otorrino | D16: 60000 | E16: 40
A17: 8 | B17: Tenis | D17: 23000 | E17: 15.33
A18: 9 | B18: Internet | D18: 13748 | E18: 9.17
A19: 10 | B19: Alquiler Cancha Tenis | D19: 24000 | E19: 16
A20: 11 | B20: Haras Jodita | D20: 25000 | E20: 16.67
A21: 12 | B21: Racing x3 | D21: 30000 | E21: 20
A22: TOTAL FIJOS | D22: =SUM(D10:D21) | E22: =SUM(E10:E21)
A24: 📋 GASTOS DEL MES
A25: # | B25: Date | C25: Description | D25: ARS | E25: USD | F25: Category | G25: Payment
A26: 1 | B26: 01 | C26: Shell | D26: 59000 | E26: =IF(D26>0,D26/B$2,"")
A27: 2 | B27: 02 | C27: Chapita | D27: 40000 | E27: =IF(D27>0,D27/B$2,"")
A28: 3 | B28: 03 | C28: Cosmos | D28: 90000 | E28: =IF(D28>0,D28/B$2,"")
A29: 4 | B29: 04 | C29: Venti Cena | D29: 220000 | E29: =IF(D29>0,D29/B$2,"")
A30: 5 | B30: 05 | C30: Casa | D30: 225000 | E30: =IF(D30>0,D30/B$2,"")
A51: TOTAL VARIABLE | D51: =SUM(D26:D50) | E51: =SUM(E26:E50)
A53: 💰 BALANCE | D53: =D6-D22-D51 | E53: =E6-E22-E51

Sheet Feb 2026
A1: 💸 FEB 2026 — GASTOS MENSUALES
A2: USD/ARS | B2: 1500 | C2: ← update monthly
A3: ▲ INGRESOS
A4: # | B4: Source | C4: Description | D4: ARS | E4: USD
A5: 1 | C5: Basecoat | D5: 4500000 | E5: 3000
A6: TOTAL INGRESOS | D6: =SUM(D5:D5) | E6: =SUM(E5:E5)
A8: ▼ EGRESOS FIJOS
A9: # | B9: Description | C9: ARS | D9: USD | E9: Status
A10: 1 | B10: Comida y mas | D10: 900000 | E10: 600
A11: 2 | B11: Swiss Dic | D11: 172000 | E11: 114.67
A12: 3 | B12: Olav Depto | D12: 150000 | E12: 100
A13: 4 | B13: Gym | D13: 34000 | E13: 22.67
A14: 5 | B14: Psico Anab | D14: 30000 | E14: 20
A15: 6 | B15: Santander Esp | D15: 20000 | E15: 13.33
A16: 7 | B16: Otorrino | D16: 60000 | E16: 40
A17: 8 | B17: Tenis | D17: 23000 | E17: 15.33
A18: 9 | B18: Internet | D18: 13748 | E18: 9.17
A19: 10 | B19: Alquiler Cancha Tenis | D19: 24000 | E19: 16
A20: 11 | B20: Haras Jodita | D20: 25000 | E20: 16.67
A21: 12 | B21: Racing x3 | D21: 30000 | E21: 20
A22: TOTAL FIJOS | D22: =SUM(D10:D21) | E22: =SUM(E10:E21)
A24: 📋 GASTOS DEL MES
A25: # | B25: Date | C25: Description | D25: ARS | E25: USD | F25: Category | G25: Payment
A26: 1 | B26: 01 | C26: Shell | D26: 59000 | E26: =IF(D26>0,D26/B$2,"")
A27: 2 | B27: 02 | C27: Chapita | D27: 40000 | E27: =IF(D27>0,D27/B$2,"")
A28: 3 | B28: 03 | C28: Cosmos | D28: 90000 | E28: =IF(D28>0,D28/B$2,"")
A29: 4 | B29: 04 | C29: Venti Cena | D29: 220000 | E29: =IF(D29>0,D29/B$2,"")
A30: 5 | B30: 05 | C30: Casa | D30: 225000 | E30: =IF(D30>0,D30/B$2,"")
A51: TOTAL VARIABLE | D51: =SUM(D26:D50) | E51: =SUM(E26:E50)
A53: 💰 BALANCE | D53: =D6-D22-D51 | E53: =E6-E22-E51

Sheet Mar 2026
A1: 💸 MAR 2026 — GASTOS MENSUALES
A2: USD/ARS | B2: 1500 | C2: ← update monthly
A3: ▲ INGRESOS
A4: # | B4: Source | C4: Description | D4: ARS | E4: USD
A5: 1 | C5: Basecoat | D5: 3750000 | E5: 2500
A6: TOTAL INGRESOS | D6: =SUM(D5:D5) | E6: =SUM(E5:E5)
A8: ▼ EGRESOS FIJOS
A9: # | B9: Description | C9: ARS | D9: USD | E9: Status
A10: 1 | B10: Swiss Dic | D10: 194000 | E10: 129.33
A11: 2 | B11: Olav Depto | D11: 150000 | E11: 100
A12: 3 | B12: Gym Ohana | D12: 34000 | E12: 22.67
A13: 4 | B13: Psico Anab | D13: 30000 | E13: 20
A14: 5 | B14: Monotributo | D14: 50000 | E14: 33.33
A15: 6 | B15: Contadora | D15: 32000 | E15: 21.33
A16: 7 | B16: Internet | D16: 26000 | E16: 17.33
A17: 8 | B17: Bubalo Tragos | D17: 46000 | E17: 30.67
A18: 9 | B18: Bubalo Entrada | D18: 25000 | E18: 16.67
A19: 10 | B19: Pastillas | D19: 39000 | E19: 26
A20: TOTAL FIJOS | D20: =SUM(D10:D19) | E20: =SUM(E10:E19)
A22: 📋 GASTOS DEL MES
A23: # | B23: Date | C23: Description | D23: ARS | E23: USD | F23: Category | G23: Payment
A24: 1 | B24: 02 | C24: Compra ML Journal | D24: 40000 | E24: =IF(D24>0,D24/B$2,"")
A49: TOTAL VARIABLE | D49: =SUM(D24:D48) | E49: =SUM(E24:E48)
A51: 💰 BALANCE | D51: =D6-D20-D49 | E51: =E6-E20-E49

Sheet Apr 2026
A1: 💸 APR 2026 — GASTOS MENSUALES
A2: USD/ARS | B2: 1500 | C2: ← update monthly
A3: ▲ INGRESOS
A4: # | B4: Source | C4: Description | D4: ARS | E4: USD
A5: 1 | C5: Basecoat | D5: 3750000 | E5: 2500
A6: TOTAL INGRESOS | D6: =SUM(D5:D5) | E6: =SUM(E5:E5)
A8: ▼ EGRESOS FIJOS
A9: # | B9: Description | C9: ARS | D9: USD | E9: Status
A10: 1 | B10: Swiss Dic | D10: 194000 | E10: 129.33
A11: 2 | B11: Olav Depto | D11: 150000 | E11: 100
A12: 3 | B12: Gym Ohana | D12: 34000 | E12: 22.67
A13: 4 | B13: Psico Anab | D13: 30000 | E13: 20
A14: 5 | B14: Monotributo | D14: 50000 | E14: 33.33
A15: 6 | B15: Contadora | D15: 32000 | E15: 21.33
A16: 7 | B16: Psic Cognitivo | D16: 70000 | E16: 46.67
A17: 8 | B17: Internet | D17: 26000 | E17: 17.33
A18: 9 | B18: Bubalo Tragos | D18: 46000 | E18: 30.67
A19: 10 | B19: Bubalo Entrada | D19: 25000 | E19: 16.67
A20: 11 | B20: Pastillas | D20: 39000 | E20: 26
A21: 12 | B21: Gastos Abril | D21: 2200000 | E21: 1466.67
A22: TOTAL FIJOS | D22: =SUM(D10:D21) | E22: =SUM(E10:E21)
A24: 📋 GASTOS DEL MES
A25: # | B25: Date | C25: Description | D25: ARS | E25: USD | F25: Category | G25: Payment
A26: 1 | B26: 02 | C26: Compra ML Journal | D26: 40000 | E26: =IF(D26>0,D26/B$2,"")
A51: TOTAL VARIABLE | D51: =SUM(D26:D50) | E51: =SUM(E26:E50)
A53: 💰 BALANCE | D53: =D6-D22-D51 | E53: =E6-E22-E51

Sheet May 2026
A1: 💸 MAY 2026 — GASTOS MENSUALES
A2: USD/ARS | B2: 1500 | C2: ← update monthly
A3: ▲ INGRESOS
A4: # | B4: Source | C4: Description | D4: ARS | E4: USD
A5: 1 | C5: Basecoat | D5: 3750000 | E5: 2500
A6: TOTAL INGRESOS | D6: =SUM(D5:D5) | E6: =SUM(E5:E5)
A8: ▼ EGRESOS FIJOS
A9: # | B9: Description | C9: ARS | D9: USD | E9: Status
A10: 1 | B10: Swiss Dic | D10: 240000 | E10: 160
A11: 2 | B11: Gym Ohana | D11: 34000 | E11: 22.67
A12: 3 | B12: Monotributo | D12: 50000 | E12: 33.33
A13: 4 | B13: Psic test | D13: 250000 | E13: 166.67
A14: 5 | B14: Psic Cognitivo | D14: 70000 | E14: 46.67
A15: 6 | B15: Internet | D15: 26000 | E15: 17.33
A16: TOTAL FIJOS | D16: =SUM(D10:D15) | E16: =SUM(E10:E15)
A18: 📋 GASTOS DEL MES
A19: # | B19: Date | C19: Description | D19: ARS | E19: USD | F19: Category | G19: Payment
A20: 1 | B20: 02 | C20: Compra ML Journal | D20: 40000 | E20: =IF(D20>0,D20/B$2,"")
A21: 2 | B21: 19 | C21: PS5 Joystick | E21: 95
A22: 3 | B22: 25 | C22: Test pizza | D22: 15000 | E22: =IF(D22>0,D22/B$2,"")
A23: 4 | B23: 24 | C23: Nafta 208 | D23: 85000 | E23: =IF(D23>0,D23/B$2,"")
A24: 5 | B24: 25 | C24: Test directo sheets | D24: 5000 | E24: =IF(D24>0,D24/B$2,"")
A45: TOTAL VARIABLE | D45: =SUM(D20:D44) | E45: =SUM(E20:E44)
A47: 💰 BALANCE | D47: =D6-D16-D45 | E47: =E6-E16-E45

Sheet 🛍 Big Buys
A1: 🛍 ALL-TIME BIG PURCHASES
A2: Month | B2: Date | C2: Item | D2: USD | E2: ARS | F2: Notes
A3: Oct 2023 | B3: 01/10 | C3: 1er Pago Cabaña | E3: 50000
A4: Oct 2023 | B4: 03/10 | C4: 2do Pago Cabaña | E4: 118000
A5: Oct 2023 | B5: ??/10 | C5: Iphone Gonza CF 13Pro | D5: 105
A6: Nov 2023 | B6: ??/11 | C6: D Dani (deuda) | D6: 500
A7: Nov 2023 | B7: ??/11 | C7: HSBC pago | D7: 275
A8: Mar 2025 | B8: ??/03 | C8: MSI Cyborg laptop | D8: 810
A9: Mar 2025 | B9: ??/03 | C9: Sillon | E9: 230000
A10: Mar 2025 | B10: ??/03 | C10: Monitor | E10: 250000
A11: Nov 2025 | B11: ??/11 | C11: Sur Pesca | E11: 350000
A12: Nov 2025 | B12: ??/11 | C12: Chapa | E12: 250000
A13: Nov 2025 | B13: ??/11 | C13: Regalo Guido | E13: 150000
A14: Apr 2026 | B14: ??/04 | C14: Gastos Abril (varios) | D14: 1466.67 | F14: Big month
A15: May 2026 | B15: 19/05 | C15: PS5 Joystick (DualSense) | D15: 95
A16: TOTAL | D16: =SUM(D3:D15) | E16: =SUM(E3:E15)

Sheet 💰 Cash Assets
A1: 💰 CASH ASSETS — MAY 2026
A2: Asset | B2: USD Value | C2: Notes
A3: Wise (USD) | B3: 14800
A4: USD Cash (Olav) | B4: 323
A5: EUR Cash (Olav) | B5: 594 | C5: × 1.08 USD/EUR
A6: Binance USDT | B6: 0
A7: Nexo | B7: 0
A8: MercadoPago
A9: Cash ARS | B9: 40 | C9: ÷ 1500 ARS/USD
A10: Terreno (land) | B10: 30000 | C10: USD
A11: US Bank | B11: 45
A12: Level | B12: 300
A13: TOTAL ≈ USD | B13: =SUM(B3:B12)

Sheet 📊 Anual
A1: 📊 RESUMEN ANUAL
A2: Año | B2: Total Ingresos (USD) | C2: Total Egresos (USD) | D2: Balance (USD) | E2: Meses
A3: 2023 | B3: ='Oct 2023'!E14+'Nov 2023'!E10+'Dec 2023'!E8 | C3: ='Oct 2023'!E25+'Oct 2023'!E54+'Nov 2023'!E17+'Nov 2023'!E46+'Dec 2023'!E15+'Dec 2023'!E44 | D3: =B3-C3 | E3: Oct 2023, Nov 2023, Dec 2023
A4: 2024 | B4: ='Jan 2024'!E8+'Feb 2024'!E7+'Mar 2024'!E9+'Apr 2024'!E7+'May 2024'!E9+'Jun 2024'!E5+'Jul 2024'!E5+'Aug 2024'!E5+'Sep 2024'!E5+'Oct 2024'!E5+'Nov 2024'!E5+'Dec 2024'!E5 | C4: ='Jan 2024'!E15+'Jan 2024'!E44+'Feb 2024'!E14+'Feb 2024'!E43+'Mar 2024'!E16+'Mar 2024'!E45+'Apr 2024'!E14+'Apr 2024'!E43+'May 2024'!E16+'May 2024'!E45+'Jun 2024'!E9+'Jun 2024'!E38+'Jul 2024'!E9+'Jul 2024'!E38+'Aug 2024'!E9+'Aug 2024'!E38+'Sep 2024'!E9+'Sep 2024'!E38+'Oct 2024'!E9+'Oct 2024'!E38+'Nov 2024'!E9+'Nov 2024'!E38+'Dec 2024'!E9+'Dec 2024'!E38 | D4: =B4-C4 | E4: Jan 2024, Feb 2024, Mar 2024, Apr 2024, May 2024, Jun 2024, Jul 2024, Aug 2024, Sep 2024, Oct 2024, Nov 2024, Dec 2024
A5: 2025 | B5: ='Jan 2025'!E5+'Feb 2025'!E5+'Mar 2025'!E11+'Apr 2025'!E10+'May 2025'!E7+'Jun 2025'!E7+'Jul 2025'!E6+'Aug 2025'!E5+'Sep 2025'!E5+'Oct 2025'!E5+'Nov 2025'!E5+'Dec 2025'!E6 | C5: ='Jan 2025'!E9+'Jan 2025'!E38+'Feb 2025'!E9+'Feb 2025'!E38+'Mar 2025'!E25+'Mar 2025'!E54+'Apr 2025'!E22+'Apr 2025'!E51+'May 2025'!E19+'May 2025'!E48+'Jun 2025'!E19+'Jun 2025'!E48+'Jul 2025'!E18+'Jul 2025'!E47+'Aug 2025'!E19+'Aug 2025'!E48+'Sep 2025'!E16+'Sep 2025'!E45+'Oct 2025'!E17+'Oct 2025'!E46+'Nov 2025'!E22+'Nov 2025'!E51+'Dec 2025'!E18+'Dec 2025'!E47 | D5: =B5-C5 | E5: Jan 2025, Feb 2025, Mar 2025, Apr 2025, May 2025, Jun 2025, Jul 2025, Aug 2025, Sep 2025, Oct 2025, Nov 2025, Dec 2025
A6: 2026 | B6: ='Jan 2026'!E6+'Feb 2026'!E6+'Mar 2026'!E6+'Apr 2026'!E6+'May 2026'!E6 | C6: ='Jan 2026'!E22+'Jan 2026'!E51+'Feb 2026'!E22+'Feb 2026'!E51+'Mar 2026'!E20+'Mar 2026'!E49+'Apr 2026'!E22+'Apr 2026'!E51+'May 2026'!E16+'May 2026'!E45 | D6: =B6-C6 | E6: Jan 2026, Feb 2026, Mar 2026, Apr 2026, May 2026
A7: TOTAL | B7: =SUM(B3:B6) | C7: =SUM(C3:C6) | D7: =SUM(D3:D6)
